latex_dirtree_gen/__init__.py
latex_dirtree_gen/latex_dirtree_gen.py
latex_dirtree_gen-0.4.1.dist-info/LICENSE
latex_dirtree_gen-0.4.1.dist-info/METADATA
latex_dirtree_gen-0.4.1.dist-info/WHEEL
latex_dirtree_gen-0.4.1.dist-info/entry_points.txt
latex_dirtree_gen-0.4.1.dist-info/top_level.txt
latex_dirtree_gen-0.4.1.dist-info/RECORD
