Metadata-Version: 2.1
Name: latex-dirtree-gen
Version: 0.4.1
Summary: Generate dirtrees for LaTeX
Home-page: https://gitlab.com/matyashorky/latex-dirtree-gen
Author: Matyáš Horký
Author-email: info@matyashorky.cz
License: MIT
Keywords: latex,dirtree
Platform: UNKNOWN
Classifier: License :: OSI Approved :: MIT License
Classifier: Operating System :: OS Independent
Classifier: Programming Language :: Python
Classifier: Programming Language :: Python :: 3
Classifier: Programming Language :: Python :: 3.6
Classifier: Programming Language :: Python :: 3.7
Classifier: Programming Language :: Python :: 3.8
Classifier: Programming Language :: Python :: 3.9
Requires-Python: >=3.6.1
License-File: LICENSE
